zaber_bson/LICENSE
zaber_bson/__init__.py
zaber_bson/codec.py
zaber_bson/types.py
zaber_motion/__init__.py
zaber_motion/async_utils.py
zaber_motion/bindings.py
zaber_motion/call.py
zaber_motion/convert_exception.py
zaber_motion/dto_object.py
zaber_motion/events.py
zaber_motion/library.py
zaber_motion/py.typed
zaber_motion/serialization.py
zaber_motion/tools.py
zaber_motion/unit_table.py
zaber_motion/units.py
zaber_motion/version.py
zaber_motion/ascii/__init__.py
zaber_motion/ascii/all_axes.py
zaber_motion/ascii/axis.py
zaber_motion/ascii/axis_group.py
zaber_motion/ascii/axis_settings.py
zaber_motion/ascii/connection.py
zaber_motion/ascii/device.py
zaber_motion/ascii/device_io.py
zaber_motion/ascii/device_settings.py
zaber_motion/ascii/lockstep.py
zaber_motion/ascii/oscilloscope.py
zaber_motion/ascii/oscilloscope_data.py
zaber_motion/ascii/pvt.py
zaber_motion/ascii/pvt_buffer.py
zaber_motion/ascii/pvt_io.py
zaber_motion/ascii/pvt_sequence.py
zaber_motion/ascii/servo_tuner.py
zaber_motion/ascii/setting_constants.py
zaber_motion/ascii/storage.py
zaber_motion/ascii/stream.py
zaber_motion/ascii/stream_buffer.py
zaber_motion/ascii/stream_io.py
zaber_motion/ascii/streams.py
zaber_motion/ascii/transport.py
zaber_motion/ascii/trigger.py
zaber_motion/ascii/triggers.py
zaber_motion/ascii/warning_flags.py
zaber_motion/ascii/warnings.py
zaber_motion/binary/__init__.py
zaber_motion/binary/connection.py
zaber_motion/binary/device.py
zaber_motion/binary/device_settings.py
zaber_motion/dto/__init__.py
zaber_motion/dto/axis_address.py
zaber_motion/dto/channel_address.py
zaber_motion/dto/device_db_source.py
zaber_motion/dto/device_db_source_type.py
zaber_motion/dto/firmware_version.py
zaber_motion/dto/log_output_mode.py
zaber_motion/dto/measurement.py
zaber_motion/dto/named_parameter.py
zaber_motion/dto/rotation_direction.py
zaber_motion/dto/unit_conversion_descriptor.py
zaber_motion/dto/ascii/__init__.py
zaber_motion/dto/ascii/alert_event.py
zaber_motion/dto/ascii/axis_identity.py
zaber_motion-8.0.2.dist-info/LICENSE.txt
zaber_motion-8.0.2.dist-info/METADATA
zaber_motion-8.0.2.dist-info/WHEEL
zaber_motion-8.0.2.dist-info/top_level.txt
zaber_motion-8.0.2.dist-info/RECORD
