Metadata-Version: 2.1
Name: zaber_motion
Version: 8.0.2
Summary: An official library for communicating with Zaber devices.
Author-email: "Zaber Technologies Inc." <contact@zaber.com>
License: The MIT License (MIT)
Project-URL: Homepage, https://www.zaber.com/software
Project-URL: Documentation, https://software.zaber.com/motion-library
Project-URL: Repository, https://gitlab.com/ZaberTech/zaber-motion-lib
Project-URL: Issues, https://gitlab.com/ZaberTech/zaber-motion-lib/-/issues
Project-URL: Changelog, https://gitlab.com/ZaberTech/zaber-motion-lib/-/blob/master/CHANGELOG.md
Keywords: zaber,motion control,linear actuators,rotary stages
Classifier: Development Status :: 5 - Production/Stable
Classifier: Intended Audience :: Developers
Classifier: Topic :: Software Development :: Libraries
Classifier: Programming Language :: Python :: 3
Classifier: License :: OSI Approved :: MIT License
Requires-Python: >=3.8
License-File: LICENSE.txt
Requires-Dist: reactivex~=4.0
